cctvproxy
