Metadata-Version: 2.1
Name: cctvproxy
Version: 0.1.1
Summary: CCTV camera image proxy
Home-page: https://github.com/divi255/cctvproxy
Author: Sergei S.
Author-email: s@makeitwork.cz
License: MIT
Platform: UNKNOWN
Classifier: Programming Language :: Python :: 3
Classifier: License :: OSI Approved :: MIT License
Classifier: Topic :: Communications
